gptscannotation/__init__.py
gptscannotation/chat_workflow.py
gptscannotation-0.2.dist-info/METADATA
gptscannotation-0.2.dist-info/WHEEL
gptscannotation-0.2.dist-info/top_level.txt
gptscannotation-0.2.dist-info/RECORD
